aiocometd_noloop/__init__.py
aiocometd_noloop/client.py
aiocometd_noloop/constants.py
aiocometd_noloop/exceptions.py
aiocometd_noloop/extensions.py
aiocometd_noloop/typing.py
aiocometd_noloop/utils.py
aiocometd_noloop/transports/__init__.py
aiocometd_noloop/transports/abc.py
aiocometd_noloop/transports/base.py
aiocometd_noloop/transports/long_polling.py
aiocometd_noloop/transports/registry.py
aiocometd_noloop/transports/websocket.py
aiocometd_noloop-0.4.9.dist-info/LICENSE
aiocometd_noloop-0.4.9.dist-info/METADATA
aiocometd_noloop-0.4.9.dist-info/WHEEL
aiocometd_noloop-0.4.9.dist-info/top_level.txt
aiocometd_noloop-0.4.9.dist-info/RECORD
