Metadata-Version: 2.1
Name: aiocometd-noloop
Version: 0.4.9
Summary: A CometD client, updated for Python 3.10
Author-email: Robert Marki <gsmiko@gmail.com>, Kieran Lock <kieran.lock@outlook.com>
License: MIT License
Project-URL: GitHub, https://github.com/Kieran-Lock/aiocometd-noloop
Project-URL: Documentation, https://aiocometd.readthedocs.io/en/latest/
Project-URL: License, https://github.com/Kieran-Lock/aiocometd-noloop/blob/main/LICENSE
Keywords: python,streaming,comet,aiohttp,asyncio,cometd,bayeux,push
Classifier: Development Status :: 3 - Alpha
Classifier: License :: OSI Approved :: MIT License
Classifier: Programming Language :: Python :: 3.10
Classifier: Intended Audience :: Developers
Requires-Python: >=3.10
License-File: LICENSE
Requires-Dist: aiohttp (<4.0,>=3.1)
Requires-Dist: importlib-metadata ; python_version < "3.10"
